{
  "version": "5",
  "dialect": "pg",
  "entries": [
    {
      "idx": 0,
      "version": "5",
      "when": 1725975480967,
      "tag": "0000_true_lily_hollister",
      "breakpoints": true
    },
    {
      "idx": 1,
      "version": "5",
      "when": 1727981978463,
      "tag": "0001_empty_changeling",
      "breakpoints": true
    },
    {
      "idx": 2,
      "version": "5",
      "when": 1727987741965,
      "tag": "0002_lonely_mantis",
      "breakpoints": true
    },
    {
      "idx": 3,
      "version": "5",
      "when": 1727988041149,
      "tag": "0003_wakeful_shaman",
      "breakpoints": true
    },
    {
      "idx": 4,
      "version": "5",
      "when": 1728054664528,
      "tag": "0004_married_santa_claus",
      "breakpoints": true
    },
    {
      "idx": 5,
      "version": "5",
      "when": 1728054736328,
      "tag": "0005_flat_blackheart",
      "breakpoints": true
    },
    {
      "idx": 6,
      "version": "5",
      "when": 1728055687473,
      "tag": "0006_loose_chat",
      "breakpoints": true
    },
    {
      "idx": 7,
      "version": "5",
      "when": 1728057724302,
      "tag": "0007_pretty_rafael_vega",
      "breakpoints": true
    },
    {
      "idx": 8,
      "version": "5",
      "when": 1728079050003,
      "tag": "0008_supreme_union_jack",
      "breakpoints": true
    },
    {
      "idx": 9,
      "version": "5",
      "when": 1728079193730,
      "tag": "0009_narrow_mojo",
      "breakpoints": true
    },
    {
      "idx": 10,
      "version": "5",
      "when": 1728079319703,
      "tag": "0010_lonely_lester",
      "breakpoints": true
    },
    {
      "idx": 11,
      "version": "5",
      "when": 1728079738852,
      "tag": "0011_blushing_stepford_cuckoos",
      "breakpoints": true
    },
    {
      "idx": 12,
      "version": "5",
      "when": 1728080058483,
      "tag": "0012_sour_talisman",
      "breakpoints": true
    },
    {
      "idx": 13,
      "version": "5",
      "when": 1728312436258,
      "tag": "0013_burly_night_thrasher",
      "breakpoints": true
    },
    {
      "idx": 14,
      "version": "5",
      "when": 1728322821491,
      "tag": "0014_overconfident_madame_hydra",
      "breakpoints": true
    },
    {
      "idx": 15,
      "version": "5",
      "when": 1729608696792,
      "tag": "0015_certain_wiccan",
      "breakpoints": true
    }
  ]
}